mutalyzer_retriever/__init__.py
mutalyzer_retriever/cli.py
mutalyzer_retriever/client.py
mutalyzer_retriever/configuration.py
mutalyzer_retriever/parser.py
mutalyzer_retriever/reference.py
mutalyzer_retriever/related.py
mutalyzer_retriever/related_schema.py
mutalyzer_retriever/request.py
mutalyzer_retriever/retriever.py
mutalyzer_retriever/schema_validation.py
mutalyzer_retriever/util.py
mutalyzer_retriever/parsers/__init__.py
mutalyzer_retriever/parsers/datasets.py
mutalyzer_retriever/parsers/ensembl_gene_lookup.py
mutalyzer_retriever/parsers/fasta.py
mutalyzer_retriever/parsers/gff3.py
mutalyzer_retriever/parsers/json_ensembl.py
mutalyzer_retriever/parsers/lrg.py
mutalyzer_retriever/sources/__init__.py
mutalyzer_retriever/sources/ensembl.py
mutalyzer_retriever/sources/lrg.py
mutalyzer_retriever/sources/ncbi.py
mutalyzer_retriever/sources/ncbi_assemblies.py
mutalyzer_retriever-0.5.2.dist-info/licenses/LICENSE
mutalyzer_retriever-0.5.2.dist-info/METADATA
mutalyzer_retriever-0.5.2.dist-info/WHEEL
mutalyzer_retriever-0.5.2.dist-info/entry_points.txt
mutalyzer_retriever-0.5.2.dist-info/top_level.txt
mutalyzer_retriever-0.5.2.dist-info/RECORD
