Metadata-Version: 2.4
Name: mutalyzer_retriever
Version: 0.5.2
Summary: Mutalyzer genomic reference retriever.
Home-page: https://github.com/mutalyzer/retriever
Author: Mihai Lefter
Author-email: M.Lefter@lumc.nl
License: MIT
Keywords: Mutalyzer,HGVS,reference,retriever,genomic
Classifier: Intended Audience :: Science/Research
Classifier: Intended Audience :: Developers
Classifier: Operating System :: OS Independent
Classifier: Programming Language :: Python :: 3
Classifier: Topic :: Scientific/Engineering :: Bio-Informatics
Classifier: Programming Language :: Python :: 3.8
Classifier: Programming Language :: Python :: 3.9
Classifier: Programming Language :: Python :: 3.10
Classifier: Programming Language :: Python :: 3.11
Classifier: Programming Language :: Python :: 3.12
Classifier: Programming Language :: Python :: 3.13
License-File: LICENSE
Requires-Dist: biopython>=1.81
Requires-Dist: bcbio-gff>=0.7.1
Requires-Dist: requests>=2.26.0
Requires-Dist: schema>=0.7.4
Provides-Extra: dev
Requires-Dist: coverage; extra == "dev"
Requires-Dist: flake8; extra == "dev"
Requires-Dist: pytest; extra == "dev"
Requires-Dist: setuptools; extra == "dev"
Requires-Dist: twine; extra == "dev"
Dynamic: license-file
